{
  "id": "little-langford-sp4",
  "name": "Little Langford",
  "village": "Little Langford",
  "town": "Salisbury",
  "county": "Wiltshire",
  "postcode": "SP4",
  "hubCity": "Salisbury",
  "regionDir": "",
  "settlementType": "",
  "subRegion": "Salisbury",
  "coords": {
    "lat": 51.1246,
    "lng": -1.8789
  },
  "coordsSource": "os-opendata:place-centre",
  "houseTypeIds": [],
  "status": "directory",
  "priceSummary": null,
  "councilTaxBand": null,
  "overview": "",
  "character": "",
  "amenities": [],
  "schools": [],
  "transport": {
    "commutes": []
  },
  "prices": {},
  "thingsToDo": [],
  "placesToEat": [],
  "pros": [],
  "cons": [],
  "whoItSuits": [],
  "broadbandMedianMbps": null,
  "nearestStation": null,
  "primarySupermarket": null,
  "images": [],
  "sources": [],
  "rightmove": {
    "locationIdentifier": "POSTCODE^808341",
    "identifierType": "POSTCODE",
    "identifierQuality": "tight",
    "resolvedAt": "2026-06-02T21:15:17.091Z"
  },
  "geofenceRadiusMi": 3,
  "searchRadiusMi": 3,
  "active": true
}
